rys/__init__.py
rys-0.1.0.dist-info/WHEEL
rys-0.1.0.dist-info/METADATA
rys-0.1.0.dist-info/RECORD
