Metadata-Version: 2.3
Name: rys
Version: 0.1.0
Summary: Reboot your system.
Keywords: 
Author: Arkadiusz Michał Ryś
Author-email: Arkadiusz Michał Ryś <Arkadiusz.Michal.Rys@gmail.com>
License: MIT License
Classifier: Development Status :: 2 - Pre-Alpha
Classifier: Intended Audience :: Developers
Classifier: License :: OSI Approved :: MIT License
Classifier: Natural Language :: English
Classifier: Programming Language :: Python :: 3
Requires-Dist: invoke>=2,<3
Requires-Dist: jinja2>=3,<4
Requires-Dist: vermin>=1,<2
Requires-Dist: ruff ; extra == 'dev'
Requires-Dist: invoke ; extra == 'dev'
Requires-Dist: vermin ; extra == 'dev'
Requires-Dist: sphinx ; extra == 'doc'
Requires-Dist: sphinx-rtd-theme ; extra == 'doc'
Requires-Dist: sphinx-tabs ; extra == 'doc'
Requires-Dist: sphinx-toolbox ; extra == 'doc'
Requires-Dist: sphinxext-opengraph ; extra == 'doc'
Requires-Dist: sphinx-notfound-page ; extra == 'doc'
Requires-Dist: sphinxcontrib-drawio ; extra == 'doc'
Requires-Dist: readthedocs-sphinx-search ; extra == 'doc'
Requires-Dist: myst-parser ; extra == 'doc'
Requires-Dist: pytest ; extra == 'test'
Requires-Python: >=3.12
Project-URL: source, https://git.rys.one/arrys/rys
Provides-Extra: dev
Provides-Extra: doc
Provides-Extra: test
